pipenv/__init__.py
pipenv/__main__.py
pipenv/__version__.py
pipenv/_compat.py
pipenv/cmdparse.py
pipenv/core.py
pipenv/environment.py
pipenv/environments.py
pipenv/exceptions.py
pipenv/help.py
pipenv/installers.py
pipenv/pep508checker.py
pipenv/pipenv.1
pipenv/progress.py
pipenv/project.py
pipenv/pyenv.py
pipenv/resolver.py
pipenv/shells.py
pipenv/utils.py
pipenv/cli/__init__.py
pipenv/cli/command.py
pipenv/cli/options.py
pipenv/patched/README.md
pipenv/patched/__init__.py
pipenv/patched/crayons.LICENSE
pipenv/patched/crayons.py
pipenv/patched/patched.txt
pipenv/patched/safety.zip
pipenv/patched/notpip/COPYING
pipenv/patched/notpip/LICENSE.BSD
pipenv/patched/notpip/LICENSE.txt
pipenv/patched/notpip/__init__.py
pipenv/patched/notpip/__main__.py
pipenv/patched/notpip/appdirs.LICENSE.txt
pipenv/patched/notpip/distro.LICENSE
pipenv/patched/notpip/ipaddress.LICENSE
pipenv/patched/notpip/packaging.LICENSE.APACHE
pipenv/patched/notpip/pyparsing.LICENSE
pipenv/patched/notpip/retrying.LICENSE
pipenv/patched/notpip/six.LICENSE
pipenv/patched/notpip/urllib3.LICENSE
pipenv/patched/notpip/webencodings.LICENSE
pipenv/patched/notpip/_internal/__init__.py
pipenv/patched/notpip/_internal/build_env.py
pipenv/patched/notpip/_internal/cache.py
pipenv/patched/notpip/_internal/configuration.py
pipenv/patched/notpip/_internal/download.py
pipenv/patched/notpip/_internal/exceptions.py
pipenv/patched/notpip/_internal/index.py
pipenv/patched/notpip/_internal/locations.py
pipenv/patched/notpip/_internal/pep425tags.py
pipenv/patched/notpip/_internal/pyproject.py
pipenv/patched/notpip/_internal/resolve.py
pipenv/patched/notpip/_internal/wheel.py
pipenv/patched/notpip/_internal/cli/__init__.py
pipenv/patched/notpip/_internal/cli/autocompletion.py
pipenv/patched/notpip/_internal/cli/base_command.py
pipenv/patched/notpip/_internal/cli/cmdoptions.py
pipenv/patched/notpip/_internal/cli/main_parser.py
pipenv/patched/notpip/_internal/cli/parser.py
pipenv/patched/notpip/_internal/cli/status_codes.py
thoth_pipenv-2020.1.29.dist-info/LICENSE
thoth_pipenv-2020.1.29.dist-info/METADATA
thoth_pipenv-2020.1.29.dist-info/WHEEL
thoth_pipenv-2020.1.29.dist-info/entry_points.txt
thoth_pipenv-2020.1.29.dist-info/top_level.txt
thoth_pipenv-2020.1.29.dist-info/RECORD
