Metadata-Version: 2.1
Name: thoth-pipenv
Version: 2020.1.29
Summary: Python Development Workflow for Humans.
Home-page: https://github.com/pypa/pipenv
Author: Kenneth Reitz
Author-email: me@kennethreitz.org
License: MIT
Platform: UNKNOWN
Classifier: License :: OSI Approved :: MIT License
Classifier: Programming Language :: Python
Classifier: Programming Language :: Python :: 2.7
Classifier: Programming Language :: Python :: 3
Classifier: Programming Language :: Python :: 3.4
Classifier: Programming Language :: Python :: 3.5
Classifier: Programming Language :: Python :: 3.6
Classifier: Programming Language :: Python :: 3.7
Classifier: Programming Language :: Python :: Implementation :: CPython
Classifier: Programming Language :: Python :: Implementation :: PyPy
Requires-Python: >=2.7,!=3.0.*,!=3.1.*,!=3.2.*,!=3.3.*
Requires-Dist: pip (>=18.0)
Requires-Dist: certifi
Requires-Dist: setuptools (>=36.2.1)
Requires-Dist: virtualenv-clone (>=0.2.5)
Requires-Dist: virtualenv
Requires-Dist: enum34 ; python_version < "3"
Requires-Dist: typing ; python_version < "3.5"
Provides-Extra: dev
Requires-Dist: towncrier ; extra == 'dev'
Requires-Dist: bs4 ; extra == 'dev'
Requires-Dist: twine ; extra == 'dev'
Requires-Dist: sphinx (<2) ; extra == 'dev'
Requires-Dist: flake8 (<4.0,>=3.3.0) ; extra == 'dev'
Requires-Dist: parver ; extra == 'dev'
Requires-Dist: invoke ; extra == 'dev'
Requires-Dist: black ; (python_version >= "3.6") and extra == 'dev'
Provides-Extra: tests
Requires-Dist: pytest (<5.0) ; extra == 'tests'
Requires-Dist: pytest-tap ; extra == 'tests'
Requires-Dist: pytest-xdist ; extra == 'tests'
Requires-Dist: flaky ; extra == 'tests'
Requires-Dist: mock ; extra == 'tests'
